lngen/__init__.py
lngen/_nbdev.py
lngen/core.py
lngen-0.0.1.dist-info/DESCRIPTION.rst
lngen-0.0.1.dist-info/METADATA
lngen-0.0.1.dist-info/RECORD
lngen-0.0.1.dist-info/WHEEL
lngen-0.0.1.dist-info/entry_points.txt
lngen-0.0.1.dist-info/metadata.json
lngen-0.0.1.dist-info/top_level.txt
