Metadata-Version: 2.0
Name: lngen
Version: 0.0.1
Summary: Lines generation library. Generates data points for differente type of lines (2D). Used to benchmark ML progress against known variation.
Home-page: https://github.com/stephan-code/lngen
Author: stephan-code
Author-email: stephan@indriyas.net
License: Apache Software License 2.0
Keywords: data,ml
Platform: UNKNOWN
Classifier: Development Status :: 3 - Alpha
Classifier: Intended Audience :: Developers
Classifier: License :: OSI Approved :: Apache Software License
Classifier: Natural Language :: English
Classifier: Programming Language :: Python :: 3.6
Classifier: Programming Language :: Python :: 3.7
Classifier: Programming Language :: Python :: 3.8
Requires-Python: >=3.6
